waveuse/__init__.py
waveuse/process.py
waveser-0.0.1.dist-info/METADATA
waveser-0.0.1.dist-info/WHEEL
waveser-0.0.1.dist-info/top_level.txt
waveser-0.0.1.dist-info/RECORD
