Metadata-Version: 2.1
Name: waveser
Version: 0.0.1
Summary: Used to process audio data.
Home-page: https://github.com/ailabnjtech/wavepro/tree/maste
Author: zhang_1998
Author-email: 727261446@qq.com
License: MIT
Keywords: test
Platform: UNKNOWN
Requires-Dist: numpy
Requires-Dist: torch
Requires-Dist: librosa
